[
  {
    "repaired_file": "openapi.json",
    "repairs": [
      {
        "issue": {
          "message": "Missing authentication scheme for GitHub API endpoints",
          "level": "error",
          "location": {
            "jsonPath": "#/components/securitySchemes"
          }
        },
        "action_taken": "Added bearerAuth security scheme with type 'http', scheme 'bearer', and appropriate description for GitHub personal access tokens",
        "source": "human",
        "timestamp": "2025-08-06T14:30:00.000000"
      },
      {
        "issue": {
          "message": "No global security requirements defined",
          "level": "error",
          "location": {
            "jsonPath": "#/security"
          }
        },
        "action_taken": "Added root-level security array with bearerAuth requirement to enable authentication for all endpoints",
        "source": "human",
        "timestamp": "2025-08-06T14:30:00.000000"
      }
    ]
  }
]