{
  "$id": "https://jentic.com/schemas/api-scorecard.schema.json",
  "source": {
    "url": "https://raw.githubusercontent.com/jentic/jentic-public-apis/refs/heads/main/apis/openapi/openbanking.org.uk/main/v1.3/openapi.json",
    "originalUrl": "https://raw.githubusercontent.com/jentic/jentic-public-apis/refs/heads/main/apis/openapi/openbanking.org.uk/main/v1.3/openapi.json",
    "apiId": "834e59bc094388ec7b8956ca9055cc37",
    "apiVersionId": "",
    "resolvedOriginalUrl": "https://raw.githubusercontent.com/OpenBankingUK/opendata-api-spec-compiled/master/opendata-swagger.json",
    "retrievedAt": "2025-09-30T13:08:01"
  },
  "oasVersion": "3.0.0",
  "artifacts": {
    "rootPath": "https://raw.githubusercontent.com/frantuma/jentic-public-apis/refs/heads/staging/staging/apis/openapi",
    "specPath": "https://raw.githubusercontent.com/frantuma/jentic-public-apis/refs/heads/staging/staging/apis/openapi/openbanking.org.uk/main/v1.3/openapi.json",
    "bundlePath": "https://raw.githubusercontent.com/frantuma/jentic-public-apis/refs/heads/staging/staging/apis/openapi/openbanking.org.uk/main/v1.3/openapi-bundled.json"
  },
  "importProcessValidation": {
    "severity": {
      "errors": 48,
      "warnings": 76,
      "info": 2
    },
    "source": {
      "repair": 2,
      "validator": 124,
      "loader": 0,
      "parser": 0,
      "comparator": 0,
      "converter": 0,
      "fs": 0
    },
    "score": 0,
    "persistentInvalidRefs": false,
    "rewrittenInvalidRefs": false
  },
  "validation": {
    "severity": {
      "errors": 24,
      "warnings": 38,
      "info": 0
    },
    "source": {
      "repair": 0,
      "validator": 62,
      "loader": 0,
      "parser": 0,
      "comparator": 0,
      "converter": 0,
      "fs": 0
    }
  },
  "references": {
    "relative": 0,
    "absolute": 1
  },
  "timestamps": {
    "added": "2025-09-30T13:08:09",
    "updated": "2025-09-30T13:08:09"
  },
  "meta": {
    "version": "v1.3",
    "vendor": "openbanking.org.uk",
    "apiName": "main"
  },
  "status": "staging",
  "bundled": true,
  "bundleSameAsRoot": true,
  "bundleSameAsImported": true,
  "score": 0
}